generate_project/__init__.py
generate_project/main.py
generate_project/templates/config.yaml
generate_project/templates/poetry-template/cookiecutter.json
generate_project/templates/poetry-template/{{cookiecutter.project_name}}/.github/workflows/docs.yml
generate_project/templates/poetry-template/{{cookiecutter.project_name}}/.github/workflows/release.yml
generate_project/templates/poetry-template/{{cookiecutter.project_name}}/.github/workflows/tests.yml
generate_project/templates/poetry-template/{{cookiecutter.project_name}}/.github/workflows/update_rtd.yml
generate_project/templates/poetry-template/{{cookiecutter.project_name}}/.gitignore
generate_project/templates/poetry-template/{{cookiecutter.project_name}}/.readthedocs.yaml
generate_project/templates/poetry-template/{{cookiecutter.project_name}}/LICENSE
generate_project/templates/poetry-template/{{cookiecutter.project_name}}/Makefile
generate_project/templates/poetry-template/{{cookiecutter.project_name}}/README.md
generate_project/templates/poetry-template/{{cookiecutter.project_name}}/docs/Makefile
generate_project/templates/poetry-template/{{cookiecutter.project_name}}/docs/_static/custom.css
generate_project/templates/poetry-template/{{cookiecutter.project_name}}/docs/api/index.md
generate_project/templates/poetry-template/{{cookiecutter.project_name}}/docs/conf.py
generate_project/templates/poetry-template/{{cookiecutter.project_name}}/docs/doc8.ini
generate_project/templates/poetry-template/{{cookiecutter.project_name}}/docs/guides/index.md
generate_project/templates/poetry-template/{{cookiecutter.project_name}}/docs/index.md
generate_project/templates/poetry-template/{{cookiecutter.project_name}}/docs/post_gen_project.py
generate_project/templates/poetry-template/{{cookiecutter.project_name}}/docs/requirements.txt
generate_project/templates/poetry-template/{{cookiecutter.project_name}}/pyproject.toml
generate_project/templates/poetry-template/{{cookiecutter.project_name}}/run.sh
generate_project-1.0.2.post1.dist-info/LICENSE
generate_project-1.0.2.post1.dist-info/METADATA
generate_project-1.0.2.post1.dist-info/WHEEL
generate_project-1.0.2.post1.dist-info/entry_points.txt
generate_project-1.0.2.post1.dist-info/RECORD
