Metadata-Version: 2.3
Name: generate-project
Version: 1.0.2.post1
Summary: A Python project generator using cookiecutter templates
Author: Antonio Pisani
Author-email: antonio.pisani@gmail.com
Requires-Python: >=3.10,<4.0
Classifier: Programming Language :: Python :: 3
Classifier: Programming Language :: Python :: 3.10
Classifier: Programming Language :: Python :: 3.11
Classifier: Programming Language :: Python :: 3.12
Classifier: Programming Language :: Python :: 3.13
Requires-Dist: cookiecutter (>=2.6.0,<3.0.0)
Requires-Dist: python-dotenv (>=1.1.0,<2.0.0)
Requires-Dist: pyyaml (>=6.0.0,<7.0.0)
Requires-Dist: types-pyyaml (>=6.0.12,<7.0.0)
Project-URL: Documentation, https://generate-project.readthedocs.io/
Project-URL: Issue Tracker, https://github.com/apisani1/generate-project/issues
Project-URL: Release Notes, https://github.com/apisani1/generate-project/releases
Project-URL: Source Code, https://github.com/apisani1/generate-project
